pdp/__init__.py
pdp/backend.py
pdp/base.py
pdp/interface.py
pdp/log.py
pdp/monitor.py
pdp/pipeline.py
pdp/utils.py
pdp-0.1.dist-info/DESCRIPTION.rst
pdp-0.1.dist-info/METADATA
pdp-0.1.dist-info/RECORD
pdp-0.1.dist-info/WHEEL
pdp-0.1.dist-info/metadata.json
pdp-0.1.dist-info/top_level.txt
