Metadata-Version: 2.0
Name: pdp
Version: 0.1
Summary: Build fast data processing pipelines easily
Home-page: https://github.com/Egor-Krivov/pdp
Author: Egor-Krivov
Author-email: e.a.krivov@gmail.com
License: MIT
Download-URL: https://github.com/Egor-Krivov/pdp/archive/v0.1.tar.gz
Keywords: pipeline parallel thread data processing augmentation
Platform: UNKNOWN
Classifier: Development Status :: 3 - Alpha
Classifier: Intended Audience :: Developers
Classifier: License :: OSI Approved :: MIT License
Classifier: Programming Language :: Python :: 3.5
Classifier: Programming Language :: Python :: 3.6
Requires-Python: >=3.5
